{
  "info": {
    "_postman_id": "1234-5678-abcd-efgh",
    "name": "Phantom Banking API",
    "description": "Collection for testing Phantom Banking API endpoints",
    "schema": "https://schema.getpostman.com/json/collection/v2.1.0/collection.json"
  },
  "item": [
    {
      "name": "Authentication",
      "item": [
        {
          "name": "Register User",
          "request": {
            "method": "POST",
            "header": [
              {
                "key": "Content-Type",
                "value": "application/json"
              }
            ],
            "url": {
              "raw": "{{base_url}}/api/auth/register/",
              "host": ["{{base_url}}"],
              "path": ["api", "auth", "register"]
            },
            "body": {
              "mode": "raw",
              "raw": "{\n    \"username\": \"testuser\",\n    \"password\": \"testpass123\",\n    \"password2\": \"testpass123\",\n    \"email\": \"test@example.com\",\n    \"first_name\": \"Test\",\n    \"last_name\": \"User\",\n    \"phone_number\": \"+1234567890\",\n    \"date_of_birth\": \"1990-01-01\"\n}"
            }
          }
        },
        {
          "name": "Register Merchant",
          "request": {
            "method": "POST",
            "header": [
              {
                "key": "Content-Type",
                "value": "application/json"
              }
            ],
            "url": {
              "raw": "{{base_url}}/api/auth/merchant-signup/",
              "host": ["{{base_url}}"],
              "path": ["api", "auth", "merchant-signup"]
            },
            "body": {
              "mode": "raw",
              "raw": "{\n    \"username\": \"merchant1\",\n    \"password\": \"merchant123\",\n    \"password2\": \"merchant123\",\n    \"email\": \"merchant@example.com\",\n    \"first_name\": \"Merchant\",\n    \"last_name\": \"User\",\n    \"phone_number\": \"+1234567890\",\n    \"business_name\": \"Test Business\",\n    \"registration_number\": \"REG123456\",\n    \"business_type\": \"retail\"\n}"
            }
          }
        },
        {
          "name": "Login",
          "request": {
            "method": "POST",
            "header": [
              {
                "key": "Content-Type",
                "value": "application/json"
              }
            ],
            "url": {
              "raw": "{{base_url}}/api/auth/login/",
              "host": ["{{base_url}}"],
              "path": ["api", "auth", "login"]
            },
            "body": {
              "mode": "raw",
              "raw": "{\n    \"username_or_email\": \"testuser\",\n    \"password\": \"testpass123\"\n}"
            }
          }
        },
        {
          "name": "Refresh Token",
          "request": {
            "method": "POST",
            "header": [
              {
                "key": "Content-Type",
                "value": "application/json"
              }
            ],
            "url": {
              "raw": "{{base_url}}/api/auth/refresh/",
              "host": ["{{base_url}}"],
              "path": ["api", "auth", "refresh"]
            },
            "body": {
              "mode": "raw",
              "raw": "{\n    \"refresh\": \"{{refresh_token}}\"\n}"
            }
          }
        },
        {
          "name": "Logout",
          "request": {
            "method": "POST",
            "header": [
              {
                "key": "Content-Type",
                "value": "application/json"
              }
            ],
            "url": {
              "raw": "{{base_url}}/api/auth/logout/",
              "host": ["{{base_url}}"],
              "path": ["api", "auth", "logout"]
            },
            "body": {
              "mode": "raw",
              "raw": "{\n    \"refresh_token\": \"{{refresh_token}}\"\n}"
            }
          }
        },
        {
          "name": "Verify Email",
          "request": {
            "method": "POST",
            "header": [
              {
                "key": "Content-Type",
                "value": "application/json"
              }
            ],
            "url": {
              "raw": "{{base_url}}/api/auth/verify-email/",
              "host": ["{{base_url}}"],
              "path": ["api", "auth", "verify-email"]
            },
            "body": {
              "mode": "raw",
              "raw": "{\n    \"token\": \"{{verification_token}}\"\n}"
            }
          }
        },
        {
          "name": "Request Password Reset",
          "request": {
            "method": "POST",
            "header": [
              {
                "key": "Content-Type",
                "value": "application/json"
              }
            ],
            "url": {
              "raw": "{{base_url}}/api/auth/request-password-reset/",
              "host": ["{{base_url}}"],
              "path": ["api", "auth", "request-password-reset"]
            },
            "body": {
              "mode": "raw",
              "raw": "{\n    \"email\": \"test@example.com\"\n}"
            }
          }
        },
        {
          "name": "Reset Password",
          "request": {
            "method": "POST",
            "header": [
              {
                "key": "Content-Type",
                "value": "application/json"
              }
            ],
            "url": {
              "raw": "{{base_url}}/api/auth/reset-password/",
              "host": ["{{base_url}}"],
              "path": ["api", "auth", "reset-password"]
            },
            "body": {
              "mode": "raw",
              "raw": "{\n    \"token\": \"{{reset_token}}\",\n    \"new_password\": \"newpass123\"\n}"
            }
          }
        }
      ]
    },
    {
      "name": "Wallets",
      "item": [
        {
          "name": "Create Wallet Request",
          "request": {
            "method": "POST",
            "header": [
              {
                "key": "Authorization",
                "value": "Bearer {{access_token}}"
              },
              {
                "key": "Content-Type",
                "value": "application/json"
              }
            ],
            "url": {
              "raw": "{{base_url}}/api/wallet-requests/",
              "host": ["{{base_url}}"],
              "path": ["api", "wallet-requests"]
            },
            "body": {
              "mode": "raw",
              "raw": "{\n    \"first_name\": \"John\",\n    \"last_name\": \"Doe\",\n    \"email\": \"john.doe@example.com\",\n    \"phone_number\": \"+1234567890\",\n    \"national_id\": \"ID123456\",\n    \"date_of_birth\": \"1990-01-01\"\n}"
            }
          }
        },
        {
          "name": "List Wallet Requests",
          "request": {
            "method": "GET",
            "header": [
              {
                "key": "Authorization",
                "value": "Bearer {{access_token}}"
              }
            ],
            "url": {
              "raw": "{{base_url}}/api/wallet-requests/",
              "host": ["{{base_url}}"],
              "path": ["api", "wallet-requests"]
            }
          }
        },
        {
          "name": "Approve Wallet Request",
          "request": {
            "method": "POST",
            "header": [
              {
                "key": "Authorization",
                "value": "Bearer {{access_token}}"
              }
            ],
            "url": {
              "raw": "{{base_url}}/api/wallet-requests/{{request_id}}/approve/",
              "host": ["{{base_url}}"],
              "path": ["api", "wallet-requests", "{{request_id}}", "approve"]
            }
          }
        },
        {
          "name": "Reject Wallet Request",
          "request": {
            "method": "POST",
            "header": [
              {
                "key": "Authorization",
                "value": "Bearer {{access_token}}"
              }
            ],
            "url": {
              "raw": "{{base_url}}/api/wallet-requests/{{request_id}}/reject/",
              "host": ["{{base_url}}"],
              "path": ["api", "wallet-requests", "{{request_id}}", "reject"]
            }
          }
        },
        {
          "name": "Get Wallet Details",
          "request": {
            "method": "GET",
            "header": [
              {
                "key": "Authorization",
                "value": "Bearer {{access_token}}"
              }
            ],
            "url": {
              "raw": "{{base_url}}/api/wallets/{{wallet_id}}/",
              "host": ["{{base_url}}"],
              "path": ["api", "wallets", "{{wallet_id}}"]
            }
          }
        },
        {
          "name": "List Merchant Wallets",
          "request": {
            "method": "GET",
            "header": [
              {
                "key": "Authorization",
                "value": "Bearer {{access_token}}"
              }
            ],
            "url": {
              "raw": "{{base_url}}/api/merchants/{{merchant_id}}/wallets/",
              "host": ["{{base_url}}"],
              "path": ["api", "merchants", "{{merchant_id}}", "wallets"]
            }
          }
        },
        {
          "name": "Block Wallet",
          "request": {
            "method": "POST",
            "header": [
              {
                "key": "Authorization",
                "value": "Bearer {{access_token}}"
              }
            ],
            "url": {
              "raw": "{{base_url}}/api/wallets/{{wallet_id}}/block/",
              "host": ["{{base_url}}"],
              "path": ["api", "wallets", "{{wallet_id}}", "block"]
            }
          }
        }
      ]
    },
    {
      "name": "KYC",
      "item": [
        {
          "name": "Submit KYC Documents",
          "request": {
            "method": "POST",
            "header": [
              {
                "key": "Authorization",
                "value": "Bearer {{access_token}}"
              }
            ],
            "url": {
              "raw": "{{base_url}}/api/kyc/submit/",
              "host": ["{{base_url}}"],
              "path": ["api", "kyc", "submit"]
            },
            "body": {
              "mode": "formdata",
              "formdata": [
                {
                  "key": "document_type",
                  "value": "id_document",
                  "type": "text"
                },
                {
                  "key": "document_file",
                  "type": "file",
                  "src": []
                }
              ]
            }
          }
        },
        {
          "name": "Verify KYC Document",
          "request": {
            "method": "POST",
            "header": [
              {
                "key": "Authorization",
                "value": "Bearer {{access_token}}"
              },
              {
                "key": "Content-Type",
                "value": "application/json"
              }
            ],
            "url": {
              "raw": "{{base_url}}/api/kyc/{{kyc_id}}/verify/",
              "host": ["{{base_url}}"],
              "path": ["api", "kyc", "{{kyc_id}}", "verify"]
            },
            "body": {
              "mode": "raw",
              "raw": "{\n    \"status\": \"verified\",\n    \"verification_notes\": \"Documents verified successfully\"\n}"
            }
          }
        },
        {
          "name": "Request FNB Account Conversion",
          "request": {
            "method": "POST",
            "header": [
              {
                "key": "Authorization",
                "value": "Bearer {{access_token}}"
              },
              {
                "key": "Content-Type",
                "value": "application/json"
              }
            ],
            "url": {
              "raw": "{{base_url}}/api/kyc/fnb-conversion/",
              "host": ["{{base_url}}"],
              "path": ["api", "kyc", "fnb-conversion"]
            },
            "body": {
              "mode": "raw",
              "raw": "{\n    \"wallet_id\": \"{{wallet_id}}\",\n    \"kyc_verification_id\": \"{{kyc_id}}\"\n}"
            }
          }
        }
      ]
    },
    {
      "name": "Merchants",
      "item": [
        {
          "name": "Register Merchant",
          "request": {
            "method": "POST",
            "header": [
              {
                "key": "Authorization",
                "value": "Bearer {{access_token}}"
              },
              {
                "key": "Content-Type",
                "value": "application/json"
              }
            ],
            "url": {
              "raw": "{{base_url}}/api/merchants/register/",
              "host": ["{{base_url}}"],
              "path": ["api", "merchants", "register"]
            },
            "body": {
              "mode": "raw",
              "raw": "{\n    \"business_name\": \"Test Business\",\n    \"registration_number\": \"REG123456\",\n    \"business_type\": \"retail\",\n    \"contact_email\": \"business@example.com\",\n    \"contact_phone\": \"+1234567890\",\n    \"address\": \"123 Business St\"\n}"
            }
          }
        },
        {
          "name": "List Merchant Customers",
          "request": {
            "method": "GET",
            "header": [
              {
                "key": "Authorization",
                "value": "Bearer {{access_token}}"
              }
            ],
            "url": {
              "raw": "{{base_url}}/api/merchants/{{merchant_id}}/customers/",
              "host": ["{{base_url}}"],
              "path": ["api", "merchants", "{{merchant_id}}", "customers"]
            }
          }
        }
      ]
    }
  ],
  "variable": [
    {
      "key": "base_url",
      "value": "http://localhost:8000"
    }
  ]
}